ezdrawingpg.py
ezdrawingtk.py
ezdrawing-0.0.10.dist-info/LICENCE
ezdrawing-0.0.10.dist-info/METADATA
ezdrawing-0.0.10.dist-info/WHEEL
ezdrawing-0.0.10.dist-info/top_level.txt
ezdrawing-0.0.10.dist-info/RECORD
